MANIFEST.in
README.md
setup.py
mountwizzard/__init__.py
mountwizzard/model001.fit
mountwizzard/mountwizzard.py
mountwizzard.egg-info/PKG-INFO
mountwizzard.egg-info/SOURCES.txt
mountwizzard.egg-info/dependency_links.txt
mountwizzard.egg-info/requires.txt
mountwizzard.egg-info/top_level.txt
mountwizzard/analyse/__init__.py
mountwizzard/analyse/analysedata.py
mountwizzard/astrometry/__init__.py
mountwizzard/astrometry/erfa.py
mountwizzard/astrometry/test_erfa.py
mountwizzard/astrometry/transform.py
mountwizzard/automation/__init__.py
mountwizzard/automation/upload_thread.py
mountwizzard/baseclasses/__init__.py
mountwizzard/baseclasses/camera.py
mountwizzard/baseclasses/widget.py
mountwizzard/camera/__init__.py
mountwizzard/camera/indicamera.py
mountwizzard/camera/maximdl.py
mountwizzard/camera/none.py
mountwizzard/camera/sgpro.py
mountwizzard/camera/theskyx.py
mountwizzard/dome/__init__.py
mountwizzard/dome/domeThread.py
mountwizzard/environment/__init__.py
mountwizzard/environment/environThread.py
mountwizzard/environment/unihedronThread.py
mountwizzard/gui/__init__.py
mountwizzard/gui/analyse_dialog_ui.py
mountwizzard/gui/coordinate_dialog_ui.py
mountwizzard/gui/image_dialog_ui.py
mountwizzard/gui/popup_dialog_ui.py
mountwizzard/gui/wizzard_main_ui.py
mountwizzard/indi/__init__.py
mountwizzard/indi/indi_client.py
mountwizzard/indi/indi_xml.py
mountwizzard/modeling/__init__.py
mountwizzard/modeling/modelPoints.py
mountwizzard/modeling/modelThread.py
mountwizzard/modeling/modelWorker.py
mountwizzard/modeling/modelpoints.py
mountwizzard/mount/__init__.py
mountwizzard/mount/ascommount.py
mountwizzard/mount/ipdirect.py
mountwizzard/mount/mountThread.py
mountwizzard/relays/__init__.py
mountwizzard/relays/relays.py
mountwizzard/remote/__init__.py
mountwizzard/remote/remoteThread.py
mountwizzard/widgets/__init__.py
mountwizzard/widgets/analyseWindow.py
mountwizzard/widgets/analysewindow.py
mountwizzard/widgets/imageWindow.py
mountwizzard/widgets/imagewindow.py
mountwizzard/widgets/modelplotWindow.py
mountwizzard/widgets/modelplotwindow.py
mountwizzard/widgets/popup.py