Metadata-Version: 1.2
Name: mountwizzard
Version: 2.6.0.0
Summary: tooling for a 10micron mount
Home-page: https://pypi.python.org/pypi/mountwizzard
Author: mw
Author-email: michael@wuertenberger.org
License: APL 2.0
Platform: UNKNOWN
Requires-Python: ~=3.5
